Metadata-Version: 1.1
Name: rbook
Version: 0.0.1
Summary: 内存小，功能大的库！写小说再适合不过！
Home-page: https://github.com/
Author: Yanming Guo
Author-email: gyms1111@163.com
License: UNKNOWN
Platform: UNKNOWN
Classifier: Programming Language :: Python :: 3
Classifier: License :: OSI Approved :: MIT License
Classifier: Operating System :: OS Independent
